korbit/__init__.py
korbit/cli.py
korbit/constant.py
korbit/interface.py
korbit/local_file.py
korbit/login.py
korbit/scan.py
korbit/telemetry.py
korbit/update.py
korbit/version_control.py
korbit/models/__init__.py
korbit/models/issue.py
korbit/models/report.py
korbit_mentor-3.6.7.dist-info/METADATA
korbit_mentor-3.6.7.dist-info/WHEEL
korbit_mentor-3.6.7.dist-info/entry_points.txt
korbit_mentor-3.6.7.dist-info/top_level.txt
korbit_mentor-3.6.7.dist-info/RECORD
