Metadata-Version: 2.1
Name: korbit-mentor
Version: 3.6.7
Summary: Korbit mentor CLI tool will allow you to analyze any local files.
Home-page: https://www.korbit.ai
Author: Korbit Technologies Inc.
Author-email: team@korbit.ai
Keywords: SOFTWARE,DEVELOPMENT,MENTOR,ENGINEER
Classifier: Development Status :: 3 - Alpha
Classifier: Intended Audience :: Developers
Classifier: Topic :: Software Development :: Build Tools
Classifier: Programming Language :: Python :: 3.11
Requires-Dist: validators
Requires-Dist: beautifulsoup4
Requires-Dist: click
Requires-Dist: rich
Requires-Dist: requests
Requires-Dist: gitpython
